{
  "content": [
    {
      "content": null,
      "created": "2022-02-15T10:17:49.241925Z",
      "format": null,
      "last_modified": "2022-02-15T10:16:09.956816Z",
      "mimetype": null,
      "name": "javascript.ipynb",
      "path": "javascript.ipynb",
      "size": 2179,
      "type": "notebook",
      "writable": true
    },
    {
      "content": null,
      "created": "2022-02-15T10:17:49.241925Z",
      "format": null,
      "last_modified": "2022-02-15T10:16:09.956816Z",
      "mimetype": null,
      "name": "p5.ipynb",
      "path": "p5.ipynb",
      "size": 3717,
      "type": "notebook",
      "writable": true
    },
    {
      "content": null,
      "created": "2022-02-15T10:17:49.249925Z",
      "format": null,
      "last_modified": "2022-02-15T10:17:49.249925Z",
      "mimetype": null,
      "name": "talks",
      "path": "talks",
      "size": null,
      "type": "directory",
      "writable": true
    },
    {
      "content": null,
      "created": "2022-02-15T10:17:49.249925Z",
      "format": null,
      "last_modified": "2022-02-15T10:17:49.249925Z",
      "mimetype": null,
      "name": "xeus-lua",
      "path": "xeus-lua",
      "size": null,
      "type": "directory",
      "writable": true
    },
    {
      "content": null,
      "created": "2022-02-15T10:17:49.245925Z",
      "format": null,
      "last_modified": "2022-02-15T10:16:09.956816Z",
      "mimetype": null,
      "name": "pyolite.ipynb",
      "path": "pyolite.ipynb",
      "size": 3526,
      "type": "notebook",
      "writable": true
    },
    {
      "content": null,
      "created": "2022-02-15T10:17:49.241925Z",
      "format": null,
      "last_modified": "2022-02-15T10:17:49.241925Z",
      "mimetype": null,
      "name": "data",
      "path": "data",
      "size": null,
      "type": "directory",
      "writable": true
    },
    {
      "content": null,
      "created": "2022-02-15T10:17:49.241925Z",
      "format": null,
      "last_modified": "2022-02-15T10:16:09.956816Z",
      "mimetype": "image/png",
      "name": "matplotlib.png",
      "path": "matplotlib.png",
      "size": 26389,
      "type": "file",
      "writable": true
    },
    {
      "content": null,
      "created": "2022-02-15T10:17:49.245925Z",
      "format": null,
      "last_modified": "2022-02-15T10:17:49.245925Z",
      "mimetype": null,
      "name": "pyolite",
      "path": "pyolite",
      "size": null,
      "type": "directory",
      "writable": true
    },
    {
      "content": null,
      "created": "2022-02-15T10:17:49.241925Z",
      "format": null,
      "last_modified": "2022-02-15T10:16:09.956816Z",
      "mimetype": "text/plain",
      "name": "plugin.txt",
      "path": "plugin.txt",
      "size": 637,
      "type": "file",
      "writable": true
    },
    {
      "content": null,
      "created": "2022-02-15T10:17:49.237925Z",
      "format": null,
      "last_modified": "2022-02-15T10:17:47.529906Z",
      "mimetype": "text/markdown",
      "name": "README.md",
      "path": "README.md",
      "size": 377,
      "type": "file",
      "writable": true
    }
  ],
  "created": "2022-02-15T10:17:49.249925Z",
  "format": "json",
  "last_modified": "2022-02-15T10:17:49.249925Z",
  "mimetype": null,
  "name": "",
  "path": "",
  "size": null,
  "type": "directory",
  "writable": true
}